CHANGES.txt
LICENSE
MANIFEST.in
README.rst
setup.py
we/__init__.py
we/run.py
we/utils.py
we/wechat.py
we/contrib/__init__.py
we/contrib/chatroom_analytics.py
we/contrib/friend_label.py
we/contrib/html_exporter.py
we/contrib/html_exporter_res/wechat.html
we/contrib/html_exporter_res/css/style.css
we/contrib/html_exporter_res/img/default.jpeg
we/contrib/html_exporter_res/img/testimg.jpeg
wechat_exporter.egg-info/PKG-INFO
wechat_exporter.egg-info/SOURCES.txt
wechat_exporter.egg-info/dependency_links.txt
wechat_exporter.egg-info/entry_points.txt
wechat_exporter.egg-info/not-zip-safe
wechat_exporter.egg-info/requires.txt
wechat_exporter.egg-info/top_level.txt